{"Path":"","Timestamp":1600115783380,"Items":[{"TypeId":3,"Type":"Codeunit","Id":60000,"Name":"SPA Purchase Functions","TargetObject":"","TargetObjectType":"Page","Publisher":"Prodware","Application":"SPA_Purchase","Version":"16.3.0.24","CanExecute":false,"CanDesign":false,"FsPath":"","EventName":"FctOnNewPO","EventType":"EventSubscriber","EventPublisher":false,"TargetEventName":"OnNewRecordEvent","TargetElementName":"","EventParameters":[{"IsVar":true,"Name":"Rec","TypeDefinition":{"Name":"Record","Subtype":{"Name":"Purchase Header","Id":38,"IsEmpty":false},"Temporary":false}}],"FieldName":"","SymbolData":null},{"TypeId":3,"Type":"Codeunit","Id":60000,"Name":"SPA Purchase Functions","TargetObject":"","TargetObjectType":"Page","Publisher":"Prodware","Application":"SPA_Purchase","Version":"16.3.0.24","CanExecute":false,"CanDesign":false,"FsPath":"","EventName":"FctOnBeforeReleasePO_Card","EventType":"EventSubscriber","EventPublisher":false,"TargetEventName":"OnBeforeActionEvent","TargetElementName":"Release","EventParameters":[{"IsVar":true,"Name":"Rec","TypeDefinition":{"Name":"Record","Subtype":{"Name":"Purchase Header","Id":38,"IsEmpty":false},"Temporary":false}}],"FieldName":"","SymbolData":null},{"TypeId":3,"Type":"Codeunit","Id":60000,"Name":"SPA Purchase Functions","TargetObject":"","TargetObjectType":"Page","Publisher":"Prodware","Application":"SPA_Purchase","Version":"16.3.0.24","CanExecute":false,"CanDesign":false,"FsPath":"","EventName":"FctOnBeforeReleasePO_List","EventType":"EventSubscriber","EventPublisher":false,"TargetEventName":"OnBeforeActionEvent","TargetElementName":"Release","EventParameters":[{"IsVar":true,"Name":"Rec","TypeDefinition":{"Name":"Record","Subtype":{"Name":"Purchase Header","Id":38,"IsEmpty":false},"Temporary":false}}],"FieldName":"","SymbolData":null}],"CreatedwithVersion":"0.2.4"}
